kgcreator/__init__.py
kgcreator/__main__.py
kgcreator/cli.py
kgcreator/kgcreator.py
kgcreator-0.11.dist-info/LICENSE
kgcreator-0.11.dist-info/METADATA
kgcreator-0.11.dist-info/WHEEL
kgcreator-0.11.dist-info/entry_points.txt
kgcreator-0.11.dist-info/top_level.txt
kgcreator-0.11.dist-info/RECORD
