Metadata-Version: 2.1
Name: kgcreator
Version: 0.11
Summary: Knowledge Graph Creator: converts text to RDF triples
Home-page: https://github.com/mark-watson/kgcreator
Author: Mark Watson
License: Apache License, Version 2.0
Project-URL: Issues, https://github.com/mark-watson/kgcreator/issues
Project-URL: CI, https://github.com/mark-watson/kgcreator/actions
Project-URL: Changelog, https://github.com/mark-watson/kgcreator/releases
Requires-Python: >=3.7
License-File: LICENSE
Requires-Dist: click
Requires-Dist: spacy
Provides-Extra: test
Requires-Dist: pytest ; extra == 'test'
